plotink/__init__.py
plotink/ebb3_motion.py
plotink/ebb3_serial.py
plotink/ebb_calc.py
plotink/ebb_motion.py
plotink/ebb_serial.py
plotink/plot_utils.py
plotink/plot_utils_import.py
plotink/rtree.py
plotink/spatial_grid.py
plotink/text_utils.py
plotink-1.14.0.dist-info/licenses/LICENSE
plotink-1.14.0.dist-info/METADATA
plotink-1.14.0.dist-info/WHEEL
plotink-1.14.0.dist-info/top_level.txt
plotink-1.14.0.dist-info/RECORD
