Metadata-Version: 2.4
Name: plotink
Version: 1.14.0
Summary: Helper routines for use with plotters
Home-page: https://github.com/evil-mad/plotink
Author: Bantam Tools
Author-email: hello@bantamtools.com
Classifier: Programming Language :: Python :: 3 :: Only
Classifier: License :: OSI Approved :: MIT License
Classifier: Operating System :: OS Independent
Classifier: Development Status :: 5 - Production/Stable
Classifier: Natural Language :: English
Classifier: Intended Audience :: Developers
Requires-Python: >=3.6.0
License-File: LICENSE
Requires-Dist: ink_extensions>=2.2.0
Requires-Dist: packaging>=21.0
Requires-Dist: pyserial>=3.5
Provides-Extra: dev
Requires-Dist: coverage; extra == "dev"
Provides-Extra: test
Dynamic: author
Dynamic: author-email
Dynamic: classifier
Dynamic: description
Dynamic: description-content-type
Dynamic: home-page
Dynamic: license-file
Dynamic: provides-extra
Dynamic: requires-dist
Dynamic: requires-python
Dynamic: summary
